gama_config/__init__.py
gama_config/gama_gs.py
gama_config/gama_gs_io.py
gama_config/gama_vessel.py
gama_config/gama_vessel_io.py
gama_config/generate_schemas.py
gama_config/helpers.py
gama_config/schemas/gama_gs.schema.json
gama_config/schemas/gama_vessel.schema.json
gama_config/test/helpers.py
gama_config/test/test_gama_gs_io.py
gama_config/test/test_gama_vessel_io.py
gama_config-4.5.1.dist-info/METADATA
gama_config-4.5.1.dist-info/WHEEL
gama_config-4.5.1.dist-info/top_level.txt
gama_config-4.5.1.dist-info/zip-safe
gama_config-4.5.1.dist-info/RECORD
