Metadata-Version: 2.4
Name: gama_config
Version: 4.5.1
Summary: A library for reading / writing GAMA config files
Home-page: https://github.com/Greenroom-Robotics/gama
Author: Greenroom Robotics
Author-email: team@greenroomrobotics.com
Maintainer: David Revay
Maintainer-email: david.revay@greenroomrobotics.com
License: Copyright (C) 2023, Greenroom Robotics
Keywords: colcon
Classifier: Development Status :: 3 - Alpha
Classifier: Environment :: Plugins
Classifier: Intended Audience :: Developers
Classifier: Programming Language :: Python
Classifier: Topic :: Software Development :: Build Tools
Requires-Dist: setuptools
Requires-Dist: dacite
Requires-Dist: PyYAML
Requires-Dist: greenstream-config<5.0,>=4.0
